tq_recursive_scroll_scrape/__init__.py
tq_recursive_scroll_scrape/recursive_scroll_and_scrape.py
tq_recursive_scroll_scrape-3.0.dist-info/LICENSE
tq_recursive_scroll_scrape-3.0.dist-info/METADATA
tq_recursive_scroll_scrape-3.0.dist-info/WHEEL
tq_recursive_scroll_scrape-3.0.dist-info/top_level.txt
tq_recursive_scroll_scrape-3.0.dist-info/RECORD
