Metadata-Version: 2.1
Name: tq-recursive-scroll-scrape
Version: 3.0
Summary: recursive-scroll-scrape module.
Home-page: https://github.com/farooq-teqniqly/tq-recursive-scroll-scrape
Author: Teqniqly
Author-email: farooq@teqniqly.com
License: MIT
Project-URL: GitHub, https://github.com/farooq-teqniqly/tq-recursive-scroll-scrape
Platform: UNKNOWN
Classifier: Development Status :: 5 - Production/Stable
Classifier: Programming Language :: Python
Classifier: Programming Language :: Python :: 3 :: Only
Classifier: Intended Audience :: Developers
Classifier: License :: OSI Approved :: MIT License
Classifier: Topic :: Software Development :: Libraries :: Python Modules
Classifier: Topic :: Internet :: WWW/HTTP
Classifier: Topic :: Utilities
Requires-Python: >=3.9
License-File: LICENSE
Requires-Dist: tq-scroll-scrape
